LICENSE
MANIFEST.in
README.rst
setup.py
django_tabulate/__init__.py
django_tabulate/base.py
django_tabulate/mixins.py
django_tabulate.egg-info/PKG-INFO
django_tabulate.egg-info/SOURCES.txt
django_tabulate.egg-info/dependency_links.txt
django_tabulate.egg-info/requires.txt
django_tabulate.egg-info/top_level.txt
tests/__init__.py
tests/models.py
tests/settings.py
tests/test_mixin.py