Metadata-Version: 1.1
Name: django-tabulate
Version: 0.1.1
Summary: Pretty-print Django QuerySets.
Home-page: https://github.com/todorvelichkov/django-tabulate
Author: Todor Velichkov
Author-email: todorvelichkov89@gmail.com
License: MIT
Keywords: tabulate Pretty-print Django queryset
Platform: UNKNOWN
Classifier: Environment :: Web Environment
Classifier: Development Status :: 1 - Planning
Classifier: Framework :: Django
Classifier: Intended Audience :: Developers
Classifier: License :: OSI Approved :: MIT License
Classifier: Operating System :: OS Independent
Classifier: Programming Language :: Python
Classifier: Programming Language :: Python :: 2.7
Classifier: Programming Language :: Python :: 3
Classifier: Topic :: Software Development :: Libraries
